<disponibilites><chalet id="1000"><plage id="1" /><plage id="2" /><plage id="3" /><plage id="4" /><plage id="5" /><plage id="6" /><plage id="7" /><plage id="8" /><plage id="9" /><plage id="10" /><plage id="11" /><plage id="12" /><plage id="13" /><plage id="14" /><plage id="15" /><plage id="16" /><plage id="17" /><plage id="18" /><plage id="19" /><plage id="20" /><plage id="21" /><plage id="22" /><plage id="23" /><plage id="24" /><plage id="25" /><plage id="26" /><plage id="27" /><plage id="28" /><plage id="29" /><plage id="30" /><plage id="31" /><plage id="32" /><plage id="33" /><plage id="34" /><plage id="35" /><plage id="36" /><plage id="37" /><plage id="38" /><plage id="39" /><plage id="40" /><plage id="41" /><plage id="42" /><plage id="43" /><plage id="44" /><plage id="45" /><plage id="46" /><plage id="47" /><plage id="48" /><plage id="49" /><plage id="50" /><plage id="51" /><plage id="52" /></chalet><chalet id="1001"><plage id="1" /><plage id="2" /><plage id="3" /><plage id="4" /><plage id="5" /><plage id="6" /><plage id="7" /><plage id="8" /><plage id="9" /><plage id="10" /><plage id="11" /><plage id="12" /><plage id="13" /><plage id="14" /><plage id="15" /><plage id="16" /><plage id="17" /><plage id="18" /><plage id="19" /><plage id="20" /><plage id="21" /><plage id="22" /><plage id="23" /><plage id="24" /><plage id="25" /><plage id="26" /><plage id="27" /><plage id="28" /><plage id="29" /><plage id="30" /><plage id="31" /><plage id="32" /><plage id="33" /><plage id="34" /><plage id="35" /><plage id="36" /><plage id="37" /><plage id="38" /><plage id="39" /><plage id="40" /><plage id="41" /><plage id="42" /><plage id="43" /><plage id="44" /><plage id="45" /><plage id="46" /><plage id="47" /><plage id="48" /><plage id="49" /><plage id="50" /><plage id="51" /><plage id="52" /></chalet><chalet id="1002"><plage id="1" /><plage id="2" /><plage id="3" /><plage id="4" /><plage id="5" /><plage id="6" /><plage id="7" /><plage id="8" /><plage id="9" /><plage id="10" /><plage id="11" /><plage id="12" /><plage id="13" /><plage id="14" /><plage id="15" /><plage id="16" /><plage id="17" /><plage id="18" /><plage id="19" /><plage id="20" /><plage id="21" /><plage id="22" /><plage id="23" /><plage id="24" /><plage id="25" /><plage id="26" /><plage id="27" /><plage id="28" /><plage id="29" /><plage id="30" /><plage id="31" /><plage id="32" /><plage id="33" /><plage id="34" /><plage id="35" /><plage id="36" /><plage id="37" /><plage id="38" /><plage id="39" /><plage id="40" /><plage id="41" /><plage id="42" /><plage id="43" /><plage id="44" /><plage id="45" /><plage id="46" /><plage id="47" /><plage id="48" /><plage id="49" /><plage id="50" /><plage id="51" /><plage id="52" /></chalet><chalet id="1003"><plage id="1" /><plage id="2" /><plage id="3" /><plage id="4" /><plage id="5" /><plage id="6" /><plage id="7" /><plage id="8" /><plage id="9" /><plage id="10" /><plage id="11" /><plage id="12" /><plage id="13" /><plage id="14" /><plage id="15" /><plage id="16" /><plage id="17" /><plage id="18" /><plage id="19" /><plage id="20" /><plage id="21" /><plage id="22" /><plage id="23" /><plage id="24" /><plage id="25" /><plage id="26" /><plage id="27" /><plage id="28" /><plage id="29" /><plage id="30" /><plage id="31" /><plage id="32" /><plage id="33" /><plage id="34" /><plage id="35" /><plage id="36" /><plage id="37" /><plage id="38" /><plage id="39" /><plage id="40" /><plage id="41" /><plage id="42" /><plage id="43" /><plage id="44" /><plage id="45" /><plage id="46" /><plage id="47" /><plage id="48" /><plage id="49" /><plage id="50" /><plage id="51" /><plage id="52" /></chalet><chalet id="1004"><plage id="1" /><plage id="2" /><plage id="3" /><plage id="4" /><plage id="5" /><plage id="6" /><plage id="7" /><plage id="8" /><plage id="9" /><plage id="10" /><plage id="11" /><plage id="12" /><plage id="13" /><plage id="14" /><plage id="15" /><plage id="16" /><plage id="17" /><plage id="18" /><plage id="19" /><plage id="20" /><plage id="21" /><plage id="22" /><plage id="23" /><plage id="24" /><plage id="25" /><plage id="26" /><plage id="27" /><plage id="28" /><plage id="29" /><plage id="30" /><plage id="31" /><plage id="32" /><plage id="33" /><plage id="34" /><plage id="35" /><plage id="36" /><plage id="37" /><plage id="38" /><plage id="39" /><plage id="40" /><plage id="41" /><plage id="42" /><plage id="43" /><plage id="44" /><plage id="45" /><plage id="46" /><plage id="47" /><plage id="48" /><plage id="49" /><plage id="50" /><plage id="51" /><plage id="52" /></chalet><chalet id="1005"><plage id="1" /><plage id="2" /><plage id="3" /><plage id="4" /><plage id="5" /><plage id="6" /><plage id="7" /><plage id="8" /><plage id="9" /><plage id="10" /><plage id="11" /><plage id="12" /><plage id="13" /><plage id="14" /><plage id="15" /><plage id="16" /><plage id="17" /><plage id="18" /><plage id="19" /><plage id="20" /><plage id="21" /><plage id="22" /><plage id="23" /><plage id="24" /><plage id="25" /><plage id="26" /><plage id="27" /><plage id="28" /><plage id="29" /><plage id="30" /><plage id="31" /><plage id="32" /><plage id="33" /><plage id="34" /><plage id="35" /><plage id="36" /><plage id="37" /><plage id="38" /><plage id="39" /><plage id="40" /><plage id="41" /><plage id="42" /><plage id="43" /><plage id="44" /><plage id="45" /><plage id="46" /><plage id="47" /><plage id="48" /><plage id="49" /><plage id="50" /><plage id="51" /><plage id="52" /></chalet><chalet id="1006"><plage id="1" /><plage id="2" /><plage id="3" /><plage id="4" /><plage id="5" /><plage id="6" /><plage id="7" /><plage id="8" /><plage id="9" /><plage id="10" /><plage id="11" /><plage id="12" /><plage id="13" /><plage id="14" /><plage id="15" /><plage id="16" /><plage id="17" /><plage id="18" /><plage id="19" /><plage id="20" /><plage id="21" /><plage id="22" /><plage id="23" /><plage id="24" /><plage id="25" /><plage id="26" /><plage id="27" /><plage id="28" /><plage id="29" /><plage id="30" /><plage id="31" /><plage id="32" /><plage id="33" /><plage id="34" /><plage id="35" /><plage id="36" /><plage id="37" /><plage id="38" /><plage id="39" /><plage id="40" /><plage id="41" /><plage id="42" /><plage id="43" /><plage id="44" /><plage id="45" /><plage id="46" /><plage id="47" /><plage id="48" /><plage id="49" /><plage id="50" /><plage id="51" /><plage id="52" /></chalet><chalet id="1007"><plage id="1" /><plage id="2" /><plage id="3" /><plage id="4" /><plage id="5" /><plage id="6" /><plage id="7" /><plage id="8" /><plage id="9" /><plage id="10" /><plage id="11" /><plage id="12" /><plage id="13" /><plage id="14" /><plage id="15" /><plage id="16" /><plage id="17" /><plage id="18" /><plage id="19" /><plage id="20" /><plage id="21" /><plage id="22" /><plage id="23" /><plage id="24" /><plage id="25" /><plage id="26" /><plage id="27" /><plage id="28" /><plage id="29" /><plage id="30" /><plage id="31" /><plage id="32" /><plage id="33" /><plage id="34" /><plage id="35" /><plage id="36" /><plage id="37" /><plage id="38" /><plage id="39" /><plage id="40" /><plage id="41" /><plage id="42" /><plage id="43" /><plage id="44" /><plage id="45" /><plage id="46" /><plage id="47" /><plage id="48" /><plage id="49" /><plage id="50" /><plage id="51" /><plage id="52" /></chalet><chalet id="1008"><plage id="1" /><plage id="2" /><plage id="3" /><plage id="4" /><plage id="5" /><plage id="6" /><plage id="7" /><plage id="8" /><plage id="9" /><plage id="10" /><plage id="11" /><plage id="12" /><plage id="13" /><plage id="14" /><plage id="15" /><plage id="16" /><plage id="17" /><plage id="18" /><plage id="19" /><plage id="20" /><plage id="21" /><plage id="22" /><plage id="23" /><plage id="24" /><plage id="25" /><plage id="26" /><plage id="27" /><plage id="28" /><plage id="29" /><plage id="30" /><plage id="31" /><plage id="32" /><plage id="33" /><plage id="34" /><plage id="35" /><plage id="36" /><plage id="37" /><plage id="38" /><plage id="39" /><plage id="40" /><plage id="41" /><plage id="42" /><plage id="43" /><plage id="44" /><plage id="45" /><plage id="46" /><plage id="47" /><plage id="48" /><plage id="49" /><plage id="50" /><plage id="51" /><plage id="52" /></chalet><chalet id="1009"><plage id="1" /><plage id="2" /><plage id="3" /><plage id="4" /><plage id="5" /><plage id="6" /><plage id="7" /><plage id="8" /><plage id="9" /><plage id="10" /><plage id="11" /><plage id="12" /><plage id="13" /><plage id="14" /><plage id="15" /><plage id="16" /><plage id="17" /><plage id="18" /><plage id="19" /><plage id="20" /><plage id="21" /><plage id="22" /><plage id="23" /><plage id="24" /><plage id="25" /><plage id="26" /><plage id="27" /><plage id="28" /><plage id="29" /><plage id="30" /><plage id="31" /><plage id="32" /><plage id="33" /><plage id="34" /><plage id="35" /><plage id="36" /><plage id="37" /><plage id="38" /><plage id="39" /><plage id="40" /><plage id="41" /><plage id="42" /><plage id="43" /><plage id="44" /><plage id="45" /><plage id="46" /><plage id="47" /><plage id="48" /><plage id="49" /><plage id="50" /><plage id="51" /><plage id="52" /></chalet><chalet id="1010"><plage id="1" /><plage id="2" /><plage id="3" /><plage id="4" /><plage id="5" /><plage id="6" /><plage id="7" /><plage id="8" /><plage id="9" /><plage id="10" /><plage id="11" /><plage id="12" /><plage id="13" /><plage id="14" /><plage id="15" /><plage id="16" /><plage id="17" /><plage id="18" /><plage id="19" /><plage id="20" /><plage id="21" /><plage id="22" /><plage id="23" /><plage id="24" /><plage id="25" /><plage id="26" /><plage id="27" /><plage id="28" /><plage id="29" /><plage id="30" /><plage id="31" /><plage id="32" /><plage id="33" /><plage id="34" /><plage id="35" /><plage id="36" /><plage id="37" /><plage id="38" /><plage id="39" /><plage id="40" /><plage id="41" /><plage id="42" /><plage id="43" /><plage id="44" /><plage id="45" /><plage id="46" /><plage id="47" /><plage id="48" /><plage id="49" /><plage id="50" /><plage id="51" /><plage id="52" /></chalet><chalet id="1011"><plage id="1" /><plage id="2" /><plage id="3" /><plage id="4" /><plage id="5" /><plage id="6" /><plage id="7" /><plage id="8" /><plage id="9" /><plage id="10" /><plage id="11" /><plage id="12" /><plage id="13" /><plage id="14" /><plage id="15" /><plage id="16" /><plage id="17" /><plage id="18" /><plage id="19" /><plage id="20" /><plage id="21" /><plage id="22" /><plage id="23" /><plage id="24" /><plage id="25" /><plage id="26" /><plage id="27" /><plage id="28" /><plage id="29" /><plage id="30" /><plage id="31" /><plage id="32" /><plage id="33" /><plage id="34" /><plage id="35" /><plage id="36" /><plage id="37" /><plage id="38" /><plage id="39" /><plage id="40" /><plage id="41" /><plage id="42" /><plage id="43" /><plage id="44" /><plage id="45" /><plage id="46" /><plage id="47" /><plage id="48" /><plage id="49" /><plage id="50" /><plage id="51" /><plage id="52" /></chalet><chalet id="1012"><plage id="1" /><plage id="2" /><plage id="3" /><plage id="4" /><plage id="5" /><plage id="6" /><plage id="7" /><plage id="8" /><plage id="9" /><plage id="10" /><plage id="11" /><plage id="12" /><plage id="13" /><plage id="14" /><plage id="15" /><plage id="16" /><plage id="17" /><plage id="18" /><plage id="19" /><plage id="20" /><plage id="21" /><plage id="22" /><plage id="23" /><plage id="24" /><plage id="25" /><plage id="26" /><plage id="27" /><plage id="28" /><plage id="29" /><plage id="30" /><plage id="31" /><plage id="32" /><plage id="33" /><plage id="34" /><plage id="35" /><plage id="36" /><plage id="37" /><plage id="38" /><plage id="39" /><plage id="40" /><plage id="41" /><plage id="42" /><plage id="43" /><plage id="44" /><plage id="45" /><plage id="46" /><plage id="47" /><plage id="48" /><plage id="49" /><plage id="50" /><plage id="51" /><plage id="52" /></chalet><chalet id="1013"><plage id="1" /><plage id="2" /><plage id="3" /><plage id="4" /><plage id="5" /><plage id="6" /><plage id="7" /><plage id="8" /><plage id="9" /><plage id="10" /><plage id="11" /><plage id="12" /><plage id="13" /><plage id="14" /><plage id="15" /><plage id="16" /><plage id="17" /><plage id="18" /><plage id="19" /><plage id="20" /><plage id="21" /><plage id="22" /><plage id="23" /><plage id="24" /><plage id="25" /><plage id="26" /><plage id="27" /><plage id="28" /><plage id="29" /><plage id="30" /><plage id="31" /><plage id="32" /><plage id="33" /><plage id="34" /><plage id="35" /><plage id="36" /><plage id="37" /><plage id="38" /><plage id="39" /><plage id="40" /><plage id="41" /><plage id="42" /><plage id="43" /><plage id="44" /><plage id="45" /><plage id="46" /><plage id="47" /><plage id="48" /><plage id="49" /><plage id="50" /><plage id="51" /><plage id="52" /></chalet><chalet id="1014"><plage id="1" /><plage id="2" /><plage id="3" /><plage id="4" /><plage id="5" /><plage id="6" /><plage id="7" /><plage id="8" /><plage id="9" /><plage id="10" /><plage id="11" /><plage id="12" /><plage id="13" /><plage id="14" /><plage id="15" /><plage id="16" /><plage id="17" /><plage id="18" /><plage id="19" /><plage id="20" /><plage id="21" /><plage id="22" /><plage id="23" /><plage id="24" /><plage id="25" /><plage id="26" /><plage id="27" /><plage id="28" /><plage id="29" /><plage id="30" /><plage id="31" /><plage id="32" /><plage id="33" /><plage id="34" /><plage id="35" /><plage id="36" /><plage id="37" /><plage id="38" /><plage id="39" /><plage id="40" /><plage id="41" /><plage id="42" /><plage id="43" /><plage id="44" /><plage id="45" /><plage id="46" /><plage id="47" /><plage id="48" /><plage id="49" /><plage id="50" /><plage id="51" /><plage id="52" /></chalet><chalet id="1015"><plage id="1" /><plage id="2" /><plage id="3" /><plage id="4" /><plage id="5" /><plage id="6" /><plage id="7" /><plage id="8" /><plage id="9" /><plage id="10" /><plage id="11" /><plage id="12" /><plage id="13" /><plage id="14" /><plage id="15" /><plage id="16" /><plage id="17" /><plage id="18" /><plage id="19" /><plage id="20" /><plage id="21" /><plage id="22" /><plage id="23" /><plage id="24" /><plage id="25" /><plage id="26" /><plage id="27" /><plage id="28" /><plage id="29" /><plage id="30" /><plage id="31" /><plage id="32" /><plage id="33" /><plage id="34" /><plage id="35" /><plage id="36" /><plage id="37" /><plage id="38" /><plage id="39" /><plage id="40" /><plage id="41" /><plage id="42" /><plage id="43" /><plage id="44" /><plage id="45" /><plage id="46" /><plage id="47" /><plage id="48" /><plage id="49" /><plage id="50" /><plage id="51" /><plage id="52" /></chalet><chalet id="1016"><plage id="1" /><plage id="2" /><plage id="3" /><plage id="4" /><plage id="5" /><plage id="6" /><plage id="7" /><plage id="8" /><plage id="9" /><plage id="10" /><plage id="11" /><plage id="12" /><plage id="13" /><plage id="14" /><plage id="15" /><plage id="16" /><plage id="17" /><plage id="18" /><plage id="19" /><plage id="20" /><plage id="21" /><plage id="22" /><plage id="23" /><plage id="24" /><plage id="25" /><plage id="26" /><plage id="27" /><plage id="28" /><plage id="29" /><plage id="30" /><plage id="31" /><plage id="32" /><plage id="33" /><plage id="34" /><plage id="35" /><plage id="36" /><plage id="37" /><plage id="38" /><plage id="39" /><plage id="40" /><plage id="41" /><plage id="42" /><plage id="43" /><plage id="44" /><plage id="45" /><plage id="46" /><plage id="47" /><plage id="48" /><plage id="49" /><plage id="50" /><plage id="51" /><plage id="52" /></chalet><chalet id="1017"><plage id="1" /><plage id="2" /><plage id="3" /><plage id="4" /><plage id="5" /><plage id="6" /><plage id="7" /><plage id="8" /><plage id="9" /><plage id="10" /><plage id="11" /><plage id="12" /><plage id="13" /><plage id="14" /><plage id="15" /><plage id="16" /><plage id="17" /><plage id="18" /><plage id="19" /><plage id="20" /><plage id="21" /><plage id="22" /><plage id="23" /><plage id="24" /><plage id="25" /><plage id="26" /><plage id="27" /><plage id="28" /><plage id="29" /><plage id="30" /><plage id="31" /><plage id="32" /><plage id="33" /><plage id="34" /><plage id="35" /><plage id="36" /><plage id="37" /><plage id="38" /><plage id="39" /><plage id="40" /><plage id="41" /><plage id="42" /><plage id="43" /><plage id="44" /><plage id="45" /><plage id="46" /><plage id="47" /><plage id="48" /><plage id="49" /><plage id="50" /><plage id="51" /><plage id="52" /></chalet><chalet id="1018"><plage id="1" /><plage id="2" /><plage id="3" /><plage id="4" /><plage id="5" /><plage id="6" /><plage id="7" /><plage id="8" /><plage id="9" /><plage id="10" /><plage id="11" /><plage id="12" /><plage id="13" /><plage id="14" /><plage id="15" /><plage id="16" /><plage id="17" /><plage id="18" /><plage id="19" /><plage id="20" /><plage id="21" /><plage id="22" /><plage id="23" /><plage id="24" /><plage id="25" /><plage id="26" /><plage id="27" /><plage id="28" /><plage id="29" /><plage id="30" /><plage id="31" /><plage id="32" /><plage id="33" /><plage id="34" /><plage id="35" /><plage id="36" /><plage id="37" /><plage id="38" /><plage id="39" /><plage id="40" /><plage id="41" /><plage id="42" /><plage id="43" /><plage id="44" /><plage id="45" /><plage id="46" /><plage id="47" /><plage id="48" /><plage id="49" /><plage id="50" /><plage id="51" /><plage id="52" /></chalet><chalet id="1019"><plage id="1" /><plage id="2" /><plage id="3" /><plage id="4" /><plage id="5" /><plage id="6" /><plage id="7" /><plage id="8" /><plage id="9" /><plage id="10" /><plage id="11" /><plage id="12" /><plage id="13" /><plage id="14" /><plage id="15" /><plage id="16" /><plage id="17" /><plage id="18" /><plage id="19" /><plage id="20" /><plage id="21" /><plage id="22" /><plage id="23" /><plage id="24" /><plage id="25" /><plage id="26" /><plage id="27" /><plage id="28" /><plage id="29" /><plage id="30" /><plage id="31" /><plage id="32" /><plage id="33" /><plage id="34" /><plage id="35" /><plage id="36" /><plage id="37" /><plage id="38" /><plage id="39" /><plage id="40" /><plage id="41" /><plage id="42" /><plage id="43" /><plage id="44" /><plage id="45" /><plage id="46" /><plage id="47" /><plage id="48" /><plage id="49" /><plage id="50" /><plage id="51" /><plage id="52" /></chalet><chalet id="1020"><plage id="1" /><plage id="2" /><plage id="3" /><plage id="4" /><plage id="5" /><plage id="6" /><plage id="7" /><plage id="8" /><plage id="9" /><plage id="10" /><plage id="11" /><plage id="12" /><plage id="13" /><plage id="14" /><plage id="15" /><plage id="16" /><plage id="17" /><plage id="18" /><plage id="19" /><plage id="20" /><plage id="21" /><plage id="22" /><plage id="23" /><plage id="24" /><plage id="25" /><plage id="26" /><plage id="27" /><plage id="28" /><plage id="29" /><plage id="30" /><plage id="31" /><plage id="32" /><plage id="33" /><plage id="34" /><plage id="35" /><plage id="36" /><plage id="37" /><plage id="38" /><plage id="39" /><plage id="40" /><plage id="41" /><plage id="42" /><plage id="43" /><plage id="44" /><plage id="45" /><plage id="46" /><plage id="47" /><plage id="48" /><plage id="49" /><plage id="50" /><plage id="51" /><plage id="52" /></chalet><chalet id="1021"><plage id="1" /><plage id="2" /><plage id="3" /><plage id="4" /><plage id="5" /><plage id="6" /><plage id="7" /><plage id="8" /><plage id="9" /><plage id="10" /><plage id="11" /><plage id="12" /><plage id="13" /><plage id="14" /><plage id="15" /><plage id="16" /><plage id="17" /><plage id="18" /><plage id="19" /><plage id="20" /><plage id="21" /><plage id="22" /><plage id="23" /><plage id="24" /><plage id="25" /><plage id="26" /><plage id="27" /><plage id="28" /><plage id="29" /><plage id="30" /><plage id="31" /><plage id="32" /><plage id="33" /><plage id="34" /><plage id="35" /><plage id="36" /><plage id="37" /><plage id="38" /><plage id="39" /><plage id="40" /><plage id="41" /><plage id="42" /><plage id="43" /><plage id="44" /><plage id="45" /><plage id="46" /><plage id="47" /><plage id="48" /><plage id="49" /><plage id="50" /><plage id="51" /><plage id="52" /></chalet><chalet id="1022"><plage id="1" /><plage id="2" /><plage id="3" /><plage id="4" /><plage id="5" /><plage id="6" /><plage id="7" /><plage id="8" /><plage id="9" /><plage id="10" /><plage id="11" /><plage id="12" /><plage id="13" /><plage id="14" /><plage id="15" /><plage id="16" /><plage id="17" /><plage id="18" /><plage id="19" /><plage id="20" /><plage id="21" /><plage id="22" /><plage id="23" /><plage id="24" /><plage id="25" /><plage id="26" /><plage id="27" /><plage id="28" /><plage id="29" /><plage id="30" /><plage id="31" /><plage id="32" /><plage id="33" /><plage id="34" /><plage id="35" /><plage id="36" /><plage id="37" /><plage id="38" /><plage id="39" /><plage id="40" /><plage id="41" /><plage id="42" /><plage id="43" /><plage id="44" /><plage id="45" /><plage id="46" /><plage id="47" /><plage id="48" /><plage id="49" /><plage id="50" /><plage id="51" /><plage id="52" /></chalet><chalet id="1023"><plage id="1" /><plage id="2" /><plage id="3" /><plage id="4" /><plage id="5" /><plage id="6" /><plage id="7" /><plage id="8" /><plage id="9" /><plage id="10" /><plage id="11" /><plage id="12" /><plage id="13" /><plage id="14" /><plage id="15" /><plage id="16" /><plage id="17" /><plage id="18" /><plage id="19" /><plage id="20" /><plage id="21" /><plage id="22" /><plage id="23" /><plage id="24" /><plage id="25" /><plage id="26" /><plage id="27" /><plage id="28" /><plage id="29" /><plage id="30" /><plage id="31" /><plage id="32" /><plage id="33" /><plage id="34" /><plage id="35" /><plage id="36" /><plage id="37" /><plage id="38" /><plage id="39" /><plage id="40" /><plage id="41" /><plage id="42" /><plage id="43" /><plage id="44" /><plage id="45" /><plage id="46" /><plage id="47" /><plage id="48" /><plage id="49" /><plage id="50" /><plage id="51" /><plage id="52" /></chalet><chalet id="1024"><plage id="1" /><plage id="2" /><plage id="3" /><plage id="4" /><plage id="5" /><plage id="6" /><plage id="7" /><plage id="8" /><plage id="9" /><plage id="10" /><plage id="11" /><plage id="12" /><plage id="13" /><plage id="14" /><plage id="15" /><plage id="16" /><plage id="17" /><plage id="18" /><plage id="19" /><plage id="20" /><plage id="21" /><plage id="22" /><plage id="23" /><plage id="24" /><plage id="25" /><plage id="26" /><plage id="27" /><plage id="28" /><plage id="29" /><plage id="30" /><plage id="31" /><plage id="32" /><plage id="33" /><plage id="34" /><plage id="35" /><plage id="36" /><plage id="37" /><plage id="38" /><plage id="39" /><plage id="40" /><plage id="41" /><plage id="42" /><plage id="43" /><plage id="44" /><plage id="45" /><plage id="46" /><plage id="47" /><plage id="48" /><plage id="49" /><plage id="50" /><plage id="51" /><plage id="52" /></chalet><chalet id="1025"><plage id="1" /><plage id="2" /><plage id="3" /><plage id="4" /><plage id="5" /><plage id="6" /><plage id="7" /><plage id="8" /><plage id="9" /><plage id="10" /><plage id="11" /><plage id="12" /><plage id="13" /><plage id="14" /><plage id="15" /><plage id="16" /><plage id="17" /><plage id="18" /><plage id="19" /><plage id="20" /><plage id="21" /><plage id="22" /><plage id="23" /><plage id="24" /><plage id="25" /><plage id="26" /><plage id="27" /><plage id="28" /><plage id="29" /><plage id="30" /><plage id="31" /><plage id="32" /><plage id="33" /><plage id="34" /><plage id="35" /><plage id="36" /><plage id="37" /><plage id="38" /><plage id="39" /><plage id="40" /><plage id="41" /><plage id="42" /><plage id="43" /><plage id="44" /><plage id="45" /><plage id="46" /><plage id="47" /><plage id="48" /><plage id="49" /><plage id="50" /><plage id="51" /><plage id="52" /></chalet><chalet id="1026"><plage id="1" /><plage id="2" /><plage id="3" /><plage id="4" /><plage id="5" /><plage id="6" /><plage id="7" /><plage id="8" /><plage id="9" /><plage id="10" /><plage id="11" /><plage id="12" /><plage id="13" /><plage id="14" /><plage id="15" /><plage id="16" /><plage id="17" /><plage id="18" /><plage id="19" /><plage id="20" /><plage id="21" /><plage id="22" /><plage id="23" /><plage id="24" /><plage id="25" /><plage id="26" /><plage id="27" /><plage id="28" /><plage id="29" /><plage id="30" /><plage id="31" /><plage id="32" /><plage id="33" /><plage id="34" /><plage id="35" /><plage id="36" /><plage id="37" /><plage id="38" /><plage id="39" /><plage id="40" /><plage id="41" /><plage id="42" /><plage id="43" /><plage id="44" /><plage id="45" /><plage id="46" /><plage id="47" /><plage id="48" /><plage id="49" /><plage id="50" /><plage id="51" /><plage id="52" /></chalet><chalet id="1027"><plage id="1" /><plage id="2" /><plage id="3" /><plage id="4" /><plage id="5" /><plage id="6" /><plage id="7" /><plage id="8" /><plage id="9" /><plage id="10" /><plage id="11" /><plage id="12" /><plage id="13" /><plage id="14" /><plage id="15" /><plage id="16" /><plage id="17" /><plage id="18" /><plage id="19" /><plage id="20" /><plage id="21" /><plage id="22" /><plage id="23" /><plage id="24" /><plage id="25" /><plage id="26" /><plage id="27" /><plage id="28" /><plage id="29" /><plage id="30" /><plage id="31" /><plage id="32" /><plage id="33" /><plage id="34" /><plage id="35" /><plage id="36" /><plage id="37" /><plage id="38" /><plage id="39" /><plage id="40" /><plage id="41" /><plage id="42" /><plage id="43" /><plage id="44" /><plage id="45" /><plage id="46" /><plage id="47" /><plage id="48" /><plage id="49" /><plage id="50" /><plage id="51" /><plage id="52" /></chalet><chalet id="1028"><plage id="1" /><plage id="2" /><plage id="3" /><plage id="4" /><plage id="5" /><plage id="6" /><plage id="7" /><plage id="8" /><plage id="9" /><plage id="10" /><plage id="11" /><plage id="12" /><plage id="13" /><plage id="14" /><plage id="15" /><plage id="16" /><plage id="17" /><plage id="18" /><plage id="19" /><plage id="20" /><plage id="21" /><plage id="22" /><plage id="23" /><plage id="24" /><plage id="25" /><plage id="26" /><plage id="27" /><plage id="28" /><plage id="29" /><plage id="30" /><plage id="31" /><plage id="32" /><plage id="33" /><plage id="34" /><plage id="35" /><plage id="36" /><plage id="37" /><plage id="38" /><plage id="39" /><plage id="40" /><plage id="41" /><plage id="42" /><plage id="43" /><plage id="44" /><plage id="45" /><plage id="46" /><plage id="47" /><plage id="48" /><plage id="49" /><plage id="50" /><plage id="51" /><plage id="52" /></chalet><chalet id="1029"><plage id="1" /><plage id="2" /><plage id="3" /><plage id="4" /><plage id="5" /><plage id="6" /><plage id="7" /><plage id="8" /><plage id="9" /><plage id="10" /><plage id="11" /><plage id="12" /><plage id="13" /><plage id="14" /><plage id="15" /><plage id="16" /><plage id="17" /><plage id="18" /><plage id="19" /><plage id="20" /><plage id="21" /><plage id="22" /><plage id="23" /><plage id="24" /><plage id="25" /><plage id="26" /><plage id="27" /><plage id="28" /><plage id="29" /><plage id="30" /><plage id="31" /><plage id="32" /><plage id="33" /><plage id="34" /><plage id="35" /><plage id="36" /><plage id="37" /><plage id="38" /><plage id="39" /><plage id="40" /><plage id="41" /><plage id="42" /><plage id="43" /><plage id="44" /><plage id="45" /><plage id="46" /><plage id="47" /><plage id="48" /><plage id="49" /><plage id="50" /><plage id="51" /><plage id="52" /></chalet><chalet id="1030"><plage id="1" /><plage id="2" /><plage id="3" /><plage id="4" /><plage id="5" /><plage id="6" /><plage id="7" /><plage id="8" /><plage id="9" /><plage id="10" /><plage id="11" /><plage id="12" /><plage id="13" /><plage id="14" /><plage id="15" /><plage id="16" /><plage id="17" /><plage id="18" /><plage id="19" /><plage id="20" /><plage id="21" /><plage id="22" /><plage id="23" /><plage id="24" /><plage id="25" /><plage id="26" /><plage id="27" /><plage id="28" /><plage id="29" /><plage id="30" /><plage id="31" /><plage id="32" /><plage id="33" /><plage id="34" /><plage id="35" /><plage id="36" /><plage id="37" /><plage id="38" /><plage id="39" /><plage id="40" /><plage id="41" /><plage id="42" /><plage id="43" /><plage id="44" /><plage id="45" /><plage id="46" /><plage id="47" /><plage id="48" /><plage id="49" /><plage id="50" /><plage id="51" /><plage id="52" /></chalet><chalet id="1031"><plage id="1" /><plage id="2" /><plage id="3" /><plage id="4" /><plage id="5" /><plage id="6" /><plage id="7" /><plage id="8" /><plage id="9" /><plage id="10" /><plage id="11" /><plage id="12" /><plage id="13" /><plage id="14" /><plage id="15" /><plage id="16" /><plage id="17" /><plage id="18" /><plage id="19" /><plage id="20" /><plage id="21" /><plage id="22" /><plage id="23" /><plage id="24" /><plage id="25" /><plage id="26" /><plage id="27" /><plage id="28" /><plage id="29" /><plage id="30" /><plage id="31" /><plage id="32" /><plage id="33" /><plage id="34" /><plage id="35" /><plage id="36" /><plage id="37" /><plage id="38" /><plage id="39" /><plage id="40" /><plage id="41" /><plage id="42" /><plage id="43" /><plage id="44" /><plage id="45" /><plage id="46" /><plage id="47" /><plage id="48" /><plage id="49" /><plage id="50" /><plage id="51" /><plage id="52" /></chalet><chalet id="1032"><plage id="1" /><plage id="2" /><plage id="3" /><plage id="4" /><plage id="5" /><plage id="6" /><plage id="7" /><plage id="8" /><plage id="9" /><plage id="10" /><plage id="11" /><plage id="12" /><plage id="13" /><plage id="14" /><plage id="15" /><plage id="16" /><plage id="17" /><plage id="18" /><plage id="19" /><plage id="20" /><plage id="21" /><plage id="22" /><plage id="23" /><plage id="24" /><plage id="25" /><plage id="26" /><plage id="27" /><plage id="28" /><plage id="29" /><plage id="30" /><plage id="31" /><plage id="32" /><plage id="33" /><plage id="34" /><plage id="35" /><plage id="36" /><plage id="37" /><plage id="38" /><plage id="39" /><plage id="40" /><plage id="41" /><plage id="42" /><plage id="43" /><plage id="44" /><plage id="45" /><plage id="46" /><plage id="47" /><plage id="48" /><plage id="49" /><plage id="50" /><plage id="51" /><plage id="52" /></chalet><chalet id="1033"><plage id="1" /><plage id="2" /><plage id="3" /><plage id="4" /><plage id="5" /><plage id="6" /><plage id="7" /><plage id="8" /><plage id="9" /><plage id="10" /><plage id="11" /><plage id="12" /><plage id="13" /><plage id="14" /><plage id="15" /><plage id="16" /><plage id="17" /><plage id="18" /><plage id="19" /><plage id="20" /><plage id="21" /><plage id="22" /><plage id="23" /><plage id="24" /><plage id="25" /><plage id="26" /><plage id="27" /><plage id="28" /><plage id="29" /><plage id="30" /><plage id="31" /><plage id="32" /><plage id="33" /><plage id="34" /><plage id="35" /><plage id="36" /><plage id="37" /><plage id="38" /><plage id="39" /><plage id="40" /><plage id="41" /><plage id="42" /><plage id="43" /><plage id="44" /><plage id="45" /><plage id="46" /><plage id="47" /><plage id="48" /><plage id="49" /><plage id="50" /><plage id="51" /><plage id="52" /></chalet><chalet id="1034"><plage id="1" /><plage id="2" /><plage id="3" /><plage id="4" /><plage id="5" /><plage id="6" /><plage id="7" /><plage id="8" /><plage id="9" /><plage id="10" /><plage id="11" /><plage id="12" /><plage id="13" /><plage id="14" /><plage id="15" /><plage id="16" /><plage id="17" /><plage id="18" /><plage id="19" /><plage id="20" /><plage id="21" /><plage id="22" /><plage id="23" /><plage id="24" /><plage id="25" /><plage id="26" /><plage id="27" /><plage id="28" /><plage id="29" /><plage id="30" /><plage id="31" /><plage id="32" /><plage id="33" /><plage id="34" /><plage id="35" /><plage id="36" /><plage id="37" /><plage id="38" /><plage id="39" /><plage id="40" /><plage id="41" /><plage id="42" /><plage id="43" /><plage id="44" /><plage id="45" /><plage id="46" /><plage id="47" /><plage id="48" /><plage id="49" /><plage id="50" /><plage id="51" /><plage id="52" /></chalet><chalet id="1035"><plage id="1" /><plage id="2" /><plage id="3" /><plage id="4" /><plage id="5" /><plage id="6" /><plage id="7" /><plage id="8" /><plage id="9" /><plage id="10" /><plage id="11" /><plage id="12" /><plage id="13" /><plage id="14" /><plage id="15" /><plage id="16" /><plage id="17" /><plage id="18" /><plage id="19" /><plage id="20" /><plage id="21" /><plage id="22" /><plage id="23" /><plage id="24" /><plage id="25" /><plage id="26" /><plage id="27" /><plage id="28" /><plage id="29" /><plage id="30" /><plage id="31" /><plage id="32" /><plage id="33" /><plage id="34" /><plage id="35" /><plage id="36" /><plage id="37" /><plage id="38" /><plage id="39" /><plage id="40" /><plage id="41" /><plage id="42" /><plage id="43" /><plage id="44" /><plage id="45" /><plage id="46" /><plage id="47" /><plage id="48" /><plage id="49" /><plage id="50" /><plage id="51" /><plage id="52" /></chalet><chalet id="1036"><plage id="1" /><plage id="2" /><plage id="3" /><plage id="4" /><plage id="5" /><plage id="6" /><plage id="7" /><plage id="8" /><plage id="9" /><plage id="10" /><plage id="11" /><plage id="12" /><plage id="13" /><plage id="14" /><plage id="15" /><plage id="16" /><plage id="17" /><plage id="18" /><plage id="19" /><plage id="20" /><plage id="21" /><plage id="22" /><plage id="23" /><plage id="24" /><plage id="25" /><plage id="26" /><plage id="27" /><plage id="28" /><plage id="29" /><plage id="30" /><plage id="31" /><plage id="32" /><plage id="33" /><plage id="34" /><plage id="35" /><plage id="36" /><plage id="37" /><plage id="38" /><plage id="39" /><plage id="40" /><plage id="41" /><plage id="42" /><plage id="43" /><plage id="44" /><plage id="45" /><plage id="46" /><plage id="47" /><plage id="48" /><plage id="49" /><plage id="50" /><plage id="51" /><plage id="52" /></chalet><chalet id="1037"><plage id="1" /><plage id="2" /><plage id="3" /><plage id="4" /><plage id="5" /><plage id="6" /><plage id="7" /><plage id="8" /><plage id="9" /><plage id="10" /><plage id="11" /><plage id="12" /><plage id="13" /><plage id="14" /><plage id="15" /><plage id="16" /><plage id="17" /><plage id="18" /><plage id="19" /><plage id="20" /><plage id="21" /><plage id="22" /><plage id="23" /><plage id="24" /><plage id="25" /><plage id="26" /><plage id="27" /><plage id="28" /><plage id="29" /><plage id="30" /><plage id="31" /><plage id="32" /><plage id="33" /><plage id="34" /><plage id="35" /><plage id="36" /><plage id="37" /><plage id="38" /><plage id="39" /><plage id="40" /><plage id="41" /><plage id="42" /><plage id="43" /><plage id="44" /><plage id="45" /><plage id="46" /><plage id="47" /><plage id="48" /><plage id="49" /><plage id="50" /><plage id="51" /><plage id="52" /></chalet><chalet id="1038"><plage id="1" /><plage id="2" /><plage id="3" /><plage id="4" /><plage id="5" /><plage id="6" /><plage id="7" /><plage id="8" /><plage id="9" /><plage id="10" /><plage id="11" /><plage id="12" /><plage id="13" /><plage id="14" /><plage id="15" /><plage id="16" /><plage id="17" /><plage id="18" /><plage id="19" /><plage id="20" /><plage id="21" /><plage id="22" /><plage id="23" /><plage id="24" /><plage id="25" /><plage id="26" /><plage id="27" /><plage id="28" /><plage id="29" /><plage id="30" /><plage id="31" /><plage id="32" /><plage id="33" /><plage id="34" /><plage id="35" /><plage id="36" /><plage id="37" /><plage id="38" /><plage id="39" /><plage id="40" /><plage id="41" /><plage id="42" /><plage id="43" /><plage id="44" /><plage id="45" /><plage id="46" /><plage id="47" /><plage id="48" /><plage id="49" /><plage id="50" /><plage id="51" /><plage id="52" /></chalet><chalet id="1039"><plage id="1" /><plage id="2" /><plage id="3" /><plage id="4" /><plage id="5" /><plage id="6" /><plage id="7" /><plage id="8" /><plage id="9" /><plage id="10" /><plage id="11" /><plage id="12" /><plage id="13" /><plage id="14" /><plage id="15" /><plage id="16" /><plage id="17" /><plage id="18" /><plage id="19" /><plage id="20" /><plage id="21" /><plage id="22" /><plage id="23" /><plage id="24" /><plage id="25" /><plage id="26" /><plage id="27" /><plage id="28" /><plage id="29" /><plage id="30" /><plage id="31" /><plage id="32" /><plage id="33" /><plage id="34" /><plage id="35" /><plage id="36" /><plage id="37" /><plage id="38" /><plage id="39" /><plage id="40" /><plage id="41" /><plage id="42" /><plage id="43" /><plage id="44" /><plage id="45" /><plage id="46" /><plage id="47" /><plage id="48" /><plage id="49" /><plage id="50" /><plage id="51" /><plage id="52" /></chalet><chalet id="1040"><plage id="1" /><plage id="2" /><plage id="3" /><plage id="4" /><plage id="5" /><plage id="6" /><plage id="7" /><plage id="8" /><plage id="9" /><plage id="10" /><plage id="11" /><plage id="12" /><plage id="13" /><plage id="14" /><plage id="15" /><plage id="16" /><plage id="17" /><plage id="18" /><plage id="19" /><plage id="20" /><plage id="21" /><plage id="22" /><plage id="23" /><plage id="24" /><plage id="25" /><plage id="26" /><plage id="27" /><plage id="28" /><plage id="29" /><plage id="30" /><plage id="31" /><plage id="32" /><plage id="33" /><plage id="34" /><plage id="35" /><plage id="36" /><plage id="37" /><plage id="38" /><plage id="39" /><plage id="40" /><plage id="41" /><plage id="42" /><plage id="43" /><plage id="44" /><plage id="45" /><plage id="46" /><plage id="47" /><plage id="48" /><plage id="49" /><plage id="50" /><plage id="51" /><plage id="52" /></chalet><chalet id="1041"><plage id="1" /><plage id="2" /><plage id="3" /><plage id="4" /><plage id="5" /><plage id="6" /><plage id="7" /><plage id="8" /><plage id="9" /><plage id="10" /><plage id="11" /><plage id="12" /><plage id="13" /><plage id="14" /><plage id="15" /><plage id="16" /><plage id="17" /><plage id="18" /><plage id="19" /><plage id="20" /><plage id="21" /><plage id="22" /><plage id="23" /><plage id="24" /><plage id="25" /><plage id="26" /><plage id="27" /><plage id="28" /><plage id="29" /><plage id="30" /><plage id="31" /><plage id="32" /><plage id="33" /><plage id="34" /><plage id="35" /><plage id="36" /><plage id="37" /><plage id="38" /><plage id="39" /><plage id="40" /><plage id="41" /><plage id="42" /><plage id="43" /><plage id="44" /><plage id="45" /><plage id="46" /><plage id="47" /><plage id="48" /><plage id="49" /><plage id="50" /><plage id="51" /><plage id="52" /></chalet><chalet id="1042"><plage id="1" /><plage id="2" /><plage id="3" /><plage id="4" /><plage id="5" /><plage id="6" /><plage id="7" /><plage id="8" /><plage id="9" /><plage id="10" /><plage id="11" /><plage id="12" /><plage id="13" /><plage id="14" /><plage id="15" /><plage id="16" /><plage id="17" /><plage id="18" /><plage id="19" /><plage id="20" /><plage id="21" /><plage id="22" /><plage id="23" /><plage id="24" /><plage id="25" /><plage id="26" /><plage id="27" /><plage id="28" /><plage id="29" /><plage id="30" /><plage id="31" /><plage id="32" /><plage id="33" /><plage id="34" /><plage id="35" /><plage id="36" /><plage id="37" /><plage id="38" /><plage id="39" /><plage id="40" /><plage id="41" /><plage id="42" /><plage id="43" /><plage id="44" /><plage id="45" /><plage id="46" /><plage id="47" /><plage id="48" /><plage id="49" /><plage id="50" /><plage id="51" /><plage id="52" /></chalet><chalet id="1043"><plage id="1" /><plage id="2" /><plage id="3" /><plage id="4" /><plage id="5" /><plage id="6" /><plage id="7" /><plage id="8" /><plage id="9" /><plage id="10" /><plage id="11" /><plage id="12" /><plage id="13" /><plage id="14" /><plage id="15" /><plage id="16" /><plage id="17" /><plage id="18" /><plage id="19" /><plage id="20" /><plage id="21" /><plage id="22" /><plage id="23" /><plage id="24" /><plage id="25" /><plage id="26" /><plage id="27" /><plage id="28" /><plage id="29" /><plage id="30" /><plage id="31" /><plage id="32" /><plage id="33" /><plage id="34" /><plage id="35" /><plage id="36" /><plage id="37" /><plage id="38" /><plage id="39" /><plage id="40" /><plage id="41" /><plage id="42" /><plage id="43" /><plage id="44" /><plage id="45" /><plage id="46" /><plage id="47" /><plage id="48" /><plage id="49" /><plage id="50" /><plage id="51" /><plage id="52" /></chalet><chalet id="1044"><plage id="1" /><plage id="2" /><plage id="3" /><plage id="4" /><plage id="5" /><plage id="6" /><plage id="7" /><plage id="8" /><plage id="9" /><plage id="10" /><plage id="11" /><plage id="12" /><plage id="13" /><plage id="14" /><plage id="15" /><plage id="16" /><plage id="17" /><plage id="18" /><plage id="19" /><plage id="20" /><plage id="21" /><plage id="22" /><plage id="23" /><plage id="24" /><plage id="25" /><plage id="26" /><plage id="27" /><plage id="28" /><plage id="29" /><plage id="30" /><plage id="31" /><plage id="32" /><plage id="33" /><plage id="34" /><plage id="35" /><plage id="36" /><plage id="37" /><plage id="38" /><plage id="39" /><plage id="40" /><plage id="41" /><plage id="42" /><plage id="43" /><plage id="44" /><plage id="45" /><plage id="46" /><plage id="47" /><plage id="48" /><plage id="49" /><plage id="50" /><plage id="51" /><plage id="52" /></chalet><chalet id="1045"><plage id="1" /><plage id="2" /><plage id="3" /><plage id="4" /><plage id="5" /><plage id="6" /><plage id="7" /><plage id="8" /><plage id="9" /><plage id="10" /><plage id="11" /><plage id="12" /><plage id="13" /><plage id="14" /><plage id="15" /><plage id="16" /><plage id="17" /><plage id="18" /><plage id="19" /><plage id="20" /><plage id="21" /><plage id="22" /><plage id="23" /><plage id="24" /><plage id="25" /><plage id="26" /><plage id="27" /><plage id="28" /><plage id="29" /><plage id="30" /><plage id="31" /><plage id="32" /><plage id="33" /><plage id="34" /><plage id="35" /><plage id="36" /><plage id="37" /><plage id="38" /><plage id="39" /><plage id="40" /><plage id="41" /><plage id="42" /><plage id="43" /><plage id="44" /><plage id="45" /><plage id="46" /><plage id="47" /><plage id="48" /><plage id="49" /><plage id="50" /><plage id="51" /><plage id="52" /></chalet><chalet id="1046"><plage id="1" /><plage id="2" /><plage id="3" /><plage id="4" /><plage id="5" /><plage id="6" /><plage id="7" /><plage id="8" /><plage id="9" /><plage id="10" /><plage id="11" /><plage id="12" /><plage id="13" /><plage id="14" /><plage id="15" /><plage id="16" /><plage id="17" /><plage id="18" /><plage id="19" /><plage id="20" /><plage id="21" /><plage id="22" /><plage id="23" /><plage id="24" /><plage id="25" /><plage id="26" /><plage id="27" /><plage id="28" /><plage id="29" /><plage id="30" /><plage id="31" /><plage id="32" /><plage id="33" /><plage id="34" /><plage id="35" /><plage id="36" /><plage id="37" /><plage id="38" /><plage id="39" /><plage id="40" /><plage id="41" /><plage id="42" /><plage id="43" /><plage id="44" /><plage id="45" /><plage id="46" /><plage id="47" /><plage id="48" /><plage id="49" /><plage id="50" /><plage id="51" /><plage id="52" /></chalet><chalet id="1047"><plage id="1" /><plage id="2" /><plage id="3" /><plage id="4" /><plage id="5" /><plage id="6" /><plage id="7" /><plage id="8" /><plage id="9" /><plage id="10" /><plage id="11" /><plage id="12" /><plage id="13" /><plage id="14" /><plage id="15" /><plage id="16" /><plage id="17" /><plage id="18" /><plage id="19" /><plage id="20" /><plage id="21" /><plage id="22" /><plage id="23" /><plage id="24" /><plage id="25" /><plage id="26" /><plage id="27" /><plage id="28" /><plage id="29" /><plage id="30" /><plage id="31" /><plage id="32" /><plage id="33" /><plage id="34" /><plage id="35" /><plage id="36" /><plage id="37" /><plage id="38" /><plage id="39" /><plage id="40" /><plage id="41" /><plage id="42" /><plage id="43" /><plage id="44" /><plage id="45" /><plage id="46" /><plage id="47" /><plage id="48" /><plage id="49" /><plage id="50" /><plage id="51" /><plage id="52" /></chalet><chalet id="1048"><plage id="1" /><plage id="2" /><plage id="3" /><plage id="4" /><plage id="5" /><plage id="6" /><plage id="7" /><plage id="8" /><plage id="9" /><plage id="10" /><plage id="11" /><plage id="12" /><plage id="13" /><plage id="14" /><plage id="15" /><plage id="16" /><plage id="17" /><plage id="18" /><plage id="19" /><plage id="20" /><plage id="21" /><plage id="22" /><plage id="23" /><plage id="24" /><plage id="25" /><plage id="26" /><plage id="27" /><plage id="28" /><plage id="29" /><plage id="30" /><plage id="31" /><plage id="32" /><plage id="33" /><plage id="34" /><plage id="35" /><plage id="36" /><plage id="37" /><plage id="38" /><plage id="39" /><plage id="40" /><plage id="41" /><plage id="42" /><plage id="43" /><plage id="44" /><plage id="45" /><plage id="46" /><plage id="47" /><plage id="48" /><plage id="49" /><plage id="50" /><plage id="51" /><plage id="52" /></chalet><chalet id="1049"><plage id="1" /><plage id="2" /><plage id="3" /><plage id="4" /><plage id="5" /><plage id="6" /><plage id="7" /><plage id="8" /><plage id="9" /><plage id="10" /><plage id="11" /><plage id="12" /><plage id="13" /><plage id="14" /><plage id="15" /><plage id="16" /><plage id="17" /><plage id="18" /><plage id="19" /><plage id="20" /><plage id="21" /><plage id="22" /><plage id="23" /><plage id="24" /><plage id="25" /><plage id="26" /><plage id="27" /><plage id="28" /><plage id="29" /><plage id="30" /><plage id="31" /><plage id="32" /><plage id="33" /><plage id="34" /><plage id="35" /><plage id="36" /><plage id="37" /><plage id="38" /><plage id="39" /><plage id="40" /><plage id="41" /><plage id="42" /><plage id="43" /><plage id="44" /><plage id="45" /><plage id="46" /><plage id="47" /><plage id="48" /><plage id="49" /><plage id="50" /><plage id="51" /><plage id="52" /></chalet><chalet id="1050"><plage id="1" /><plage id="2" /><plage id="3" /><plage id="4" /><plage id="5" /><plage id="6" /><plage id="7" /><plage id="8" /><plage id="9" /><plage id="10" /><plage id="11" /><plage id="12" /><plage id="13" /><plage id="14" /><plage id="15" /><plage id="16" /><plage id="17" /><plage id="18" /><plage id="19" /><plage id="20" /><plage id="21" /><plage id="22" /><plage id="23" /><plage id="24" /><plage id="25" /><plage id="26" /><plage id="27" /><plage id="28" /><plage id="29" /><plage id="30" /><plage id="31" /><plage id="32" /><plage id="33" /><plage id="34" /><plage id="35" /><plage id="36" /><plage id="37" /><plage id="38" /><plage id="39" /><plage id="40" /><plage id="41" /><plage id="42" /><plage id="43" /><plage id="44" /><plage id="45" /><plage id="46" /><plage id="47" /><plage id="48" /><plage id="49" /><plage id="50" /><plage id="51" /><plage id="52" /></chalet><chalet id="1051"><plage id="1" /><plage id="2" /><plage id="3" /><plage id="4" /><plage id="5" /><plage id="6" /><plage id="7" /><plage id="8" /><plage id="9" /><plage id="10" /><plage id="11" /><plage id="12" /><plage id="13" /><plage id="14" /><plage id="15" /><plage id="16" /><plage id="17" /><plage id="18" /><plage id="19" /><plage id="20" /><plage id="21" /><plage id="22" /><plage id="23" /><plage id="24" /><plage id="25" /><plage id="26" /><plage id="27" /><plage id="28" /><plage id="29" /><plage id="30" /><plage id="31" /><plage id="32" /><plage id="33" /><plage id="34" /><plage id="35" /><plage id="36" /><plage id="37" /><plage id="38" /><plage id="39" /><plage id="40" /><plage id="41" /><plage id="42" /><plage id="43" /><plage id="44" /><plage id="45" /><plage id="46" /><plage id="47" /><plage id="48" /><plage id="49" /><plage id="50" /><plage id="51" /><plage id="52" /></chalet><chalet id="1052"><plage id="1" /><plage id="2" /><plage id="3" /><plage id="4" /><plage id="5" /><plage id="6" /><plage id="7" /><plage id="8" /><plage id="9" /><plage id="10" /><plage id="11" /><plage id="12" /><plage id="13" /><plage id="14" /><plage id="15" /><plage id="16" /><plage id="17" /><plage id="18" /><plage id="19" /><plage id="20" /><plage id="21" /><plage id="22" /><plage id="23" /><plage id="24" /><plage id="25" /><plage id="26" /><plage id="27" /><plage id="28" /><plage id="29" /><plage id="30" /><plage id="31" /><plage id="32" /><plage id="33" /><plage id="34" /><plage id="35" /><plage id="36" /><plage id="37" /><plage id="38" /><plage id="39" /><plage id="40" /><plage id="41" /><plage id="42" /><plage id="43" /><plage id="44" /><plage id="45" /><plage id="46" /><plage id="47" /><plage id="48" /><plage id="49" /><plage id="50" /><plage id="51" /><plage id="52" /></chalet></disponibilites>